{
  "$schema": "https://developer.microsoft.com/json-schemas/fabric/item/report/definition/visualContainer/2.4.0/schema.json",
  "name": "9ada7992e772c36c4043",
  "position": {
    "x": 11.666666666666668,
    "y": 456.66666666666669,
    "z": 6000,
    "height": 245,
    "width": 641.66666666666674,
    "tabOrder": 6000
  },
  "visual": {
    "visualType": "lineChart",
    "query": {
      "queryState": {
        "Category": {
          "projections": [
            {
              "field": {
                "Column": {
                  "Expression": {
                    "SourceRef": {
                      "Entity": "Resultaten_Opleidingsonderdelen"
                    }
                  },
                  "Property": "Periode"
                }
              },
              "queryRef": "Resultaten_Opleidingsonderdelen.Periode",
              "nativeQueryRef": "Sum of Periode",
              "active": true
            }
          ]
        },
        "Y": {
          "projections": [
            {
              "field": {
                "Measure": {
                  "Expression": {
                    "SourceRef": {
                      "Entity": "Measures_studierendement"
                    }
                  },
                  "Property": "Gemiddeld studierendement %"
                }
              },
              "queryRef": "Measures_studierendement.Gemiddeld studierendement %",
              "nativeQueryRef": "Gemiddeld studierendement %"
            }
          ]
        }
      },
      "sortDefinition": {
        "sort": [
          {
            "field": {
              "Column": {
                "Expression": {
                  "SourceRef": {
                    "Entity": "Resultaten_Opleidingsonderdelen"
                  }
                },
                "Property": "Periode"
              }
            },
            "direction": "Ascending"
          }
        ]
      }
    },
    "objects": {
      "valueAxis": [
        {
          "properties": {
            "start": {
              "expr": {
                "Literal": {
                  "Value": "0D"
                }
              }
            },
            "end": {
              "expr": {
                "Literal": {
                  "Value": "1D"
                }
              }
            },
            "invertAxis": {
              "expr": {
                "Literal": {
                  "Value": "false"
                }
              }
            },
            "show": {
              "expr": {
                "Literal": {
                  "Value": "true"
                }
              }
            },
            "switchAxisPosition": {
              "expr": {
                "Literal": {
                  "Value": "false"
                }
              }
            },
            "labelPrecision": {
              "expr": {
                "Literal": {
                  "Value": "0L"
                }
              }
            },
            "showAxisTitle": {
              "expr": {
                "Literal": {
                  "Value": "true"
                }
              }
            }
          }
        }
      ],
      "categoryAxis": [
        {
          "properties": {
            "axisType": {
              "expr": {
                "Literal": {
                  "Value": "'Categorical'"
                }
              }
            },
            "showAxisTitle": {
              "expr": {
                "Literal": {
                  "Value": "true"
                }
              }
            }
          }
        }
      ]
    },
    "visualContainerObjects": {
      "title": [
        {
          "properties": {
            "text": {
              "expr": {
                "Literal": {
                  "Value": "'Evolutie studierendement (beschikbare examenmomenten)'"
                }
              }
            },
            "fontColor": {
              "solid": {
                "color": {
                  "expr": {
                    "Literal": {
                      "Value": "'#E30046'"
                    }
                  }
                }
              }
            }
          }
        }
      ],
      "border": [
        {
          "properties": {
            "show": {
              "expr": {
                "Literal": {
                  "Value": "true"
                }
              }
            },
            "color": {
              "solid": {
                "color": {
                  "expr": {
                    "Literal": {
                      "Value": "'#B5B5B5'"
                    }
                  }
                }
              }
            },
            "radius": {
              "expr": {
                "Literal": {
                  "Value": "9D"
                }
              }
            }
          }
        }
      ]
    },
    "drillFilterOtherVisuals": true
  }
}